[
  { "make": "Toyota", "model": "Corolla", "year": "2018", "trim": "1.8 XEI", "engine": "1.8L gasolina", "fuelType": "Gasolina", "transmission": "CVT", "bodyClass": "Sedan" },
  { "make": "Toyota", "model": "Yaris", "year": "2021", "trim": "1.5 XLS", "engine": "1.5L gasolina", "fuelType": "Gasolina", "transmission": "CVT", "bodyClass": "Hatchback" },
  { "make": "Toyota", "model": "Hilux", "year": "2022", "trim": "2.8 SRV 4x4", "engine": "2.8L turbo diesel", "fuelType": "Diesel", "transmission": "Automatica", "bodyClass": "Pickup" },
  { "make": "Toyota", "model": "RAV4", "year": "2020", "trim": "2.5 Hybrid", "engine": "2.5L hibrido", "fuelType": "Hibrido", "transmission": "e-CVT", "bodyClass": "SUV" },
  { "make": "Toyota", "model": "Fortuner", "year": "2021", "trim": "2.8 SRV 4x4", "engine": "2.8L turbo diesel", "fuelType": "Diesel", "transmission": "Automatica", "bodyClass": "SUV" },
  { "make": "Toyota", "model": "Land Cruiser Prado", "year": "2019", "trim": "TX-L", "engine": "3.0L diesel", "fuelType": "Diesel", "transmission": "Automatica", "bodyClass": "SUV" },
  { "make": "Suzuki", "model": "Swift", "year": "2022", "trim": "1.2 GLX", "engine": "1.2L gasolina", "fuelType": "Gasolina", "transmission": "CVT", "bodyClass": "Hatchback" },
  { "make": "Suzuki", "model": "Vitara", "year": "2021", "trim": "1.6 GLX", "engine": "1.6L gasolina", "fuelType": "Gasolina", "transmission": "Automatica", "bodyClass": "SUV" },
  { "make": "Suzuki", "model": "Grand Vitara", "year": "2018", "trim": "2.4 4x4", "engine": "2.4L gasolina", "fuelType": "Gasolina", "transmission": "Automatica", "bodyClass": "SUV" },
  { "make": "Suzuki", "model": "Jimny", "year": "2022", "trim": "1.5 GLX 4x4", "engine": "1.5L gasolina", "fuelType": "Gasolina", "transmission": "Automatica", "bodyClass": "SUV" },
  { "make": "Suzuki", "model": "S-Presso", "year": "2022", "trim": "1.0 GL", "engine": "1.0L gasolina", "fuelType": "Gasolina", "transmission": "Manual", "bodyClass": "Hatchback" },
  { "make": "Chevrolet", "model": "Onix", "year": "2022", "trim": "1.0 Turbo Premier", "engine": "1.0L turbo gasolina", "fuelType": "Gasolina", "transmission": "Automatica", "bodyClass": "Hatchback" },
  { "make": "Chevrolet", "model": "Tracker", "year": "2022", "trim": "1.2 Turbo Premier", "engine": "1.2L turbo gasolina", "fuelType": "Gasolina", "transmission": "Automatica", "bodyClass": "SUV" },
  { "make": "Chevrolet", "model": "Spark GT", "year": "2017", "trim": "1.2 LT", "engine": "1.2L gasolina", "fuelType": "Gasolina", "transmission": "Manual", "bodyClass": "Hatchback" },
  { "make": "Chevrolet", "model": "Sail", "year": "2019", "trim": "1.5 LTZ", "engine": "1.5L gasolina", "fuelType": "Gasolina", "transmission": "Manual", "bodyClass": "Sedan" },
  { "make": "Chevrolet", "model": "Aveo", "year": "2018", "trim": "1.6 LT", "engine": "1.6L gasolina", "fuelType": "Gasolina", "transmission": "Manual", "bodyClass": "Sedan" },
  { "make": "Chevrolet", "model": "Captiva", "year": "2020", "trim": "1.5 Turbo LT", "engine": "1.5L turbo gasolina", "fuelType": "Gasolina", "transmission": "CVT", "bodyClass": "SUV" },
  { "make": "Nissan", "model": "Versa", "year": "2021", "trim": "1.6 Advance", "engine": "1.6L gasolina", "fuelType": "Gasolina", "transmission": "CVT", "bodyClass": "Sedan" },
  { "make": "Nissan", "model": "Sentra", "year": "2021", "trim": "2.0 SR", "engine": "2.0L gasolina", "fuelType": "Gasolina", "transmission": "CVT", "bodyClass": "Sedan" },
  { "make": "Nissan", "model": "Kicks", "year": "2022", "trim": "1.6 Exclusive", "engine": "1.6L gasolina", "fuelType": "Gasolina", "transmission": "CVT", "bodyClass": "SUV" },
  { "make": "Nissan", "model": "Frontier", "year": "2022", "trim": "2.3 LE 4x4", "engine": "2.3L turbo diesel", "fuelType": "Diesel", "transmission": "Automatica", "bodyClass": "Pickup" },
  { "make": "Nissan", "model": "X-Trail", "year": "2020", "trim": "2.5 Exclusive", "engine": "2.5L gasolina", "fuelType": "Gasolina", "transmission": "CVT", "bodyClass": "SUV" },
  { "make": "Nissan", "model": "March", "year": "2018", "trim": "1.6 Advance", "engine": "1.6L gasolina", "fuelType": "Gasolina", "transmission": "Manual", "bodyClass": "Hatchback" },
  { "make": "Hyundai", "model": "Accent", "year": "2019", "trim": "1.6 GLS", "engine": "1.6L gasolina", "fuelType": "Gasolina", "transmission": "Automatica", "bodyClass": "Sedan" },
  { "make": "Hyundai", "model": "Grand i10", "year": "2021", "trim": "1.2 GLS", "engine": "1.2L gasolina", "fuelType": "Gasolina", "transmission": "Manual", "bodyClass": "Hatchback" },
  { "make": "Hyundai", "model": "Tucson", "year": "2021", "trim": "2.0 GLS", "engine": "2.0L gasolina", "fuelType": "Gasolina", "transmission": "Automatica", "bodyClass": "SUV" },
  { "make": "Hyundai", "model": "Santa Fe", "year": "2019", "trim": "2.2 CRDi", "engine": "2.2L turbo diesel", "fuelType": "Diesel", "transmission": "Automatica", "bodyClass": "SUV" },
  { "make": "Hyundai", "model": "Creta", "year": "2022", "trim": "1.5 GLS", "engine": "1.5L gasolina", "fuelType": "Gasolina", "transmission": "CVT", "bodyClass": "SUV" },
  { "make": "Kia", "model": "Rio", "year": "2021", "trim": "1.4 EX", "engine": "1.4L gasolina", "fuelType": "Gasolina", "transmission": "Automatica", "bodyClass": "Sedan" },
  { "make": "Kia", "model": "Picanto", "year": "2021", "trim": "1.2 EX", "engine": "1.2L gasolina", "fuelType": "Gasolina", "transmission": "Automatica", "bodyClass": "Hatchback" },
  { "make": "Kia", "model": "Sportage", "year": "2020", "trim": "2.0 EX", "engine": "2.0L gasolina", "fuelType": "Gasolina", "transmission": "Automatica", "bodyClass": "SUV" },
  { "make": "Kia", "model": "Seltos", "year": "2022", "trim": "1.6 EX", "engine": "1.6L gasolina", "fuelType": "Gasolina", "transmission": "Automatica", "bodyClass": "SUV" },
  { "make": "Kia", "model": "Sorento", "year": "2019", "trim": "2.2 CRDi", "engine": "2.2L turbo diesel", "fuelType": "Diesel", "transmission": "Automatica", "bodyClass": "SUV" },
  { "make": "Volkswagen", "model": "Gol", "year": "2018", "trim": "1.6 Trendline", "engine": "1.6L gasolina", "fuelType": "Gasolina", "transmission": "Manual", "bodyClass": "Hatchback" },
  { "make": "Volkswagen", "model": "Polo", "year": "2021", "trim": "1.6 MSI", "engine": "1.6L gasolina", "fuelType": "Gasolina", "transmission": "Manual", "bodyClass": "Hatchback" },
  { "make": "Volkswagen", "model": "Virtus", "year": "2021", "trim": "1.6 MSI", "engine": "1.6L gasolina", "fuelType": "Gasolina", "transmission": "Automatica", "bodyClass": "Sedan" },
  { "make": "Volkswagen", "model": "T-Cross", "year": "2022", "trim": "1.0 TSI", "engine": "1.0L turbo gasolina", "fuelType": "Gasolina", "transmission": "Automatica", "bodyClass": "SUV" },
  { "make": "Volkswagen", "model": "Nivus", "year": "2022", "trim": "1.0 TSI Highline", "engine": "1.0L turbo gasolina", "fuelType": "Gasolina", "transmission": "Automatica", "bodyClass": "SUV" },
  { "make": "Volkswagen", "model": "Amarok", "year": "2021", "trim": "3.0 V6 4Motion", "engine": "3.0L turbo diesel", "fuelType": "Diesel", "transmission": "Automatica", "bodyClass": "Pickup" },
  { "make": "Renault", "model": "Logan", "year": "2020", "trim": "1.6 Intens", "engine": "1.6L gasolina", "fuelType": "Gasolina", "transmission": "Manual", "bodyClass": "Sedan" },
  { "make": "Renault", "model": "Sandero", "year": "2020", "trim": "1.6 Intens", "engine": "1.6L gasolina", "fuelType": "Gasolina", "transmission": "Manual", "bodyClass": "Hatchback" },
  { "make": "Renault", "model": "Duster", "year": "2022", "trim": "1.3 Turbo Iconic", "engine": "1.3L turbo gasolina", "fuelType": "Gasolina", "transmission": "CVT", "bodyClass": "SUV" },
  { "make": "Renault", "model": "Kwid", "year": "2022", "trim": "1.0 Zen", "engine": "1.0L gasolina", "fuelType": "Gasolina", "transmission": "Manual", "bodyClass": "Hatchback" },
  { "make": "Renault", "model": "Oroch", "year": "2021", "trim": "2.0 Outsider", "engine": "2.0L gasolina", "fuelType": "Gasolina", "transmission": "Manual", "bodyClass": "Pickup" },
  { "make": "Honda", "model": "Civic", "year": "2019", "trim": "2.0 EXL", "engine": "2.0L gasolina", "fuelType": "Gasolina", "transmission": "CVT", "bodyClass": "Sedan" },
  { "make": "Honda", "model": "City", "year": "2021", "trim": "1.5 EX", "engine": "1.5L gasolina", "fuelType": "Gasolina", "transmission": "CVT", "bodyClass": "Sedan" },
  { "make": "Honda", "model": "Fit", "year": "2018", "trim": "1.5 EX", "engine": "1.5L gasolina", "fuelType": "Gasolina", "transmission": "CVT", "bodyClass": "Hatchback" },
  { "make": "Honda", "model": "HR-V", "year": "2020", "trim": "1.8 EXL", "engine": "1.8L gasolina", "fuelType": "Gasolina", "transmission": "CVT", "bodyClass": "SUV" },
  { "make": "Honda", "model": "CR-V", "year": "2019", "trim": "1.5 Turbo Touring", "engine": "1.5L turbo gasolina", "fuelType": "Gasolina", "transmission": "CVT", "bodyClass": "SUV" },
  { "make": "Mazda", "model": "Mazda 2", "year": "2021", "trim": "1.5 Grand Touring", "engine": "1.5L gasolina", "fuelType": "Gasolina", "transmission": "Automatica", "bodyClass": "Hatchback" },
  { "make": "Mazda", "model": "Mazda 3", "year": "2021", "trim": "2.0 Grand Touring", "engine": "2.0L gasolina", "fuelType": "Gasolina", "transmission": "Automatica", "bodyClass": "Sedan" },
  { "make": "Mazda", "model": "CX-3", "year": "2020", "trim": "2.0 Grand Touring", "engine": "2.0L gasolina", "fuelType": "Gasolina", "transmission": "Automatica", "bodyClass": "SUV" },
  { "make": "Mazda", "model": "CX-5", "year": "2021", "trim": "2.5 Grand Touring", "engine": "2.5L gasolina", "fuelType": "Gasolina", "transmission": "Automatica", "bodyClass": "SUV" },
  { "make": "Mazda", "model": "BT-50", "year": "2021", "trim": "3.0 4x4", "engine": "3.0L turbo diesel", "fuelType": "Diesel", "transmission": "Automatica", "bodyClass": "Pickup" },
  { "make": "Mitsubishi", "model": "L200", "year": "2021", "trim": "2.4 GLS 4x4", "engine": "2.4L turbo diesel", "fuelType": "Diesel", "transmission": "Automatica", "bodyClass": "Pickup" },
  { "make": "Mitsubishi", "model": "Montero Sport", "year": "2020", "trim": "2.4 Dakar", "engine": "2.4L turbo diesel", "fuelType": "Diesel", "transmission": "Automatica", "bodyClass": "SUV" },
  { "make": "Mitsubishi", "model": "ASX", "year": "2019", "trim": "2.0 GLS", "engine": "2.0L gasolina", "fuelType": "Gasolina", "transmission": "CVT", "bodyClass": "SUV" },
  { "make": "Mitsubishi", "model": "Outlander", "year": "2019", "trim": "2.4 GLS", "engine": "2.4L gasolina", "fuelType": "Gasolina", "transmission": "CVT", "bodyClass": "SUV" },
  { "make": "Ford", "model": "Ranger", "year": "2021", "trim": "3.2 Limited 4x4", "engine": "3.2L turbo diesel", "fuelType": "Diesel", "transmission": "Automatica", "bodyClass": "Pickup" },
  { "make": "Ford", "model": "EcoSport", "year": "2019", "trim": "1.5 SE", "engine": "1.5L gasolina", "fuelType": "Gasolina", "transmission": "Automatica", "bodyClass": "SUV" },
  { "make": "Ford", "model": "Territory", "year": "2021", "trim": "1.5 Titanium", "engine": "1.5L turbo gasolina", "fuelType": "Gasolina", "transmission": "CVT", "bodyClass": "SUV" },
  { "make": "Ford", "model": "Fiesta", "year": "2018", "trim": "1.6 SE", "engine": "1.6L gasolina", "fuelType": "Gasolina", "transmission": "Manual", "bodyClass": "Hatchback" },
  { "make": "Fiat", "model": "Argo", "year": "2021", "trim": "1.3 Drive", "engine": "1.3L gasolina", "fuelType": "Gasolina", "transmission": "Manual", "bodyClass": "Hatchback" },
  { "make": "Fiat", "model": "Cronos", "year": "2021", "trim": "1.3 Drive", "engine": "1.3L gasolina", "fuelType": "Gasolina", "transmission": "Manual", "bodyClass": "Sedan" },
  { "make": "Fiat", "model": "Strada", "year": "2022", "trim": "1.3 Volcano", "engine": "1.3L gasolina", "fuelType": "Gasolina", "transmission": "Manual", "bodyClass": "Pickup" },
  { "make": "Fiat", "model": "Toro", "year": "2021", "trim": "2.0 Volcano 4x4", "engine": "2.0L turbo diesel", "fuelType": "Diesel", "transmission": "Automatica", "bodyClass": "Pickup" },
  { "make": "Jeep", "model": "Renegade", "year": "2021", "trim": "1.8 Longitude", "engine": "1.8L gasolina", "fuelType": "Gasolina", "transmission": "Automatica", "bodyClass": "SUV" },
  { "make": "Jeep", "model": "Compass", "year": "2021", "trim": "2.0 Longitude", "engine": "2.0L gasolina", "fuelType": "Gasolina", "transmission": "Automatica", "bodyClass": "SUV" },
  { "make": "Peugeot", "model": "208", "year": "2022", "trim": "1.6 Allure", "engine": "1.6L gasolina", "fuelType": "Gasolina", "transmission": "Automatica", "bodyClass": "Hatchback" },
  { "make": "Peugeot", "model": "2008", "year": "2021", "trim": "1.6 Allure", "engine": "1.6L gasolina", "fuelType": "Gasolina", "transmission": "Automatica", "bodyClass": "SUV" },
  { "make": "Peugeot", "model": "3008", "year": "2020", "trim": "1.6 THP GT", "engine": "1.6L turbo gasolina", "fuelType": "Gasolina", "transmission": "Automatica", "bodyClass": "SUV" },
  { "make": "Citroen", "model": "C3", "year": "2022", "trim": "1.6 Feel", "engine": "1.6L gasolina", "fuelType": "Gasolina", "transmission": "Manual", "bodyClass": "Hatchback" },
  { "make": "Citroen", "model": "C4 Cactus", "year": "2021", "trim": "1.6 THP Shine", "engine": "1.6L turbo gasolina", "fuelType": "Gasolina", "transmission": "Automatica", "bodyClass": "SUV" },
  { "make": "Chery", "model": "Tiggo 2", "year": "2021", "trim": "1.5 Luxury", "engine": "1.5L gasolina", "fuelType": "Gasolina", "transmission": "Automatica", "bodyClass": "SUV" },
  { "make": "Chery", "model": "Tiggo 4", "year": "2022", "trim": "1.5 Turbo Luxury", "engine": "1.5L turbo gasolina", "fuelType": "Gasolina", "transmission": "CVT", "bodyClass": "SUV" },
  { "make": "Chery", "model": "Tiggo 7", "year": "2022", "trim": "1.5 Turbo Pro", "engine": "1.5L turbo gasolina", "fuelType": "Gasolina", "transmission": "CVT", "bodyClass": "SUV" },
  { "make": "Chery", "model": "Tiggo 8", "year": "2022", "trim": "1.6 Turbo Pro", "engine": "1.6L turbo gasolina", "fuelType": "Gasolina", "transmission": "DCT", "bodyClass": "SUV" },
  { "make": "BYD", "model": "Dolphin", "year": "2024", "trim": "EV", "engine": "Motor electrico", "fuelType": "Electrico", "transmission": "Automatica", "bodyClass": "Hatchback" },
  { "make": "BYD", "model": "Yuan Plus", "year": "2024", "trim": "EV", "engine": "Motor electrico", "fuelType": "Electrico", "transmission": "Automatica", "bodyClass": "SUV" },
  { "make": "BYD", "model": "Song Plus", "year": "2024", "trim": "DM-i", "engine": "1.5L hibrido enchufable", "fuelType": "Hibrido", "transmission": "Automatica", "bodyClass": "SUV" },
  { "make": "Great Wall", "model": "Poer", "year": "2022", "trim": "2.0 4x4", "engine": "2.0L turbo diesel", "fuelType": "Diesel", "transmission": "Automatica", "bodyClass": "Pickup" },
  { "make": "Haval", "model": "Jolion", "year": "2023", "trim": "1.5 Turbo", "engine": "1.5L turbo gasolina", "fuelType": "Gasolina", "transmission": "DCT", "bodyClass": "SUV" },
  { "make": "Haval", "model": "H6", "year": "2023", "trim": "1.5 HEV", "engine": "1.5L hibrido", "fuelType": "Hibrido", "transmission": "DHT", "bodyClass": "SUV" },
  { "make": "JAC", "model": "S2", "year": "2021", "trim": "1.5 Luxury", "engine": "1.5L gasolina", "fuelType": "Gasolina", "transmission": "Manual", "bodyClass": "SUV" },
  { "make": "JAC", "model": "JS4", "year": "2022", "trim": "1.5 Turbo", "engine": "1.5L turbo gasolina", "fuelType": "Gasolina", "transmission": "CVT", "bodyClass": "SUV" },
  { "make": "JAC", "model": "T6", "year": "2021", "trim": "2.0 4x4", "engine": "2.0L turbo diesel", "fuelType": "Diesel", "transmission": "Manual", "bodyClass": "Pickup" },
  { "make": "MG", "model": "MG3", "year": "2022", "trim": "1.5 STD", "engine": "1.5L gasolina", "fuelType": "Gasolina", "transmission": "Automatica", "bodyClass": "Hatchback" },
  { "make": "MG", "model": "ZS", "year": "2022", "trim": "1.5 Comfort", "engine": "1.5L gasolina", "fuelType": "Gasolina", "transmission": "Automatica", "bodyClass": "SUV" },
  { "make": "MG", "model": "HS", "year": "2022", "trim": "1.5 Turbo", "engine": "1.5L turbo gasolina", "fuelType": "Gasolina", "transmission": "DCT", "bodyClass": "SUV" },
  { "make": "Changan", "model": "CS35 Plus", "year": "2022", "trim": "1.6 Elite", "engine": "1.6L gasolina", "fuelType": "Gasolina", "transmission": "Automatica", "bodyClass": "SUV" },
  { "make": "Changan", "model": "Hunter", "year": "2022", "trim": "1.9 4x4", "engine": "1.9L turbo diesel", "fuelType": "Diesel", "transmission": "Manual", "bodyClass": "Pickup" },
  { "make": "Changan", "model": "UNI-T", "year": "2023", "trim": "1.5 Turbo", "engine": "1.5L turbo gasolina", "fuelType": "Gasolina", "transmission": "DCT", "bodyClass": "SUV" },
  { "make": "Geely", "model": "Coolray", "year": "2023", "trim": "1.5 Turbo", "engine": "1.5L turbo gasolina", "fuelType": "Gasolina", "transmission": "DCT", "bodyClass": "SUV" },
  { "make": "Geely", "model": "GX3 Pro", "year": "2023", "trim": "1.5", "engine": "1.5L gasolina", "fuelType": "Gasolina", "transmission": "CVT", "bodyClass": "SUV" }
]
